querky/__init__.py
querky/annotation_generator.py
querky/attr.py
querky/base_types.py
querky/common_imports.py
querky/conn_param_config.py
querky/contract.py
querky/exceptions.py
querky/helpers.py
querky/logger.py
querky/module_constructor.py
querky/param_mapper.py
querky/querky.py
querky/query.py
querky/result_shape.py
querky/subquery.py
querky/type_constructor.py
querky/annotation_generators/__init__.py
querky/annotation_generators/classic.py
querky/backends/__init__.py
querky/backends/postgresql/__init__.py
querky/backends/postgresql/contract.py
querky/backends/postgresql/dollar_sign_param_mapper.py
querky/backends/postgresql/name_type_mapper.py
querky/backends/postgresql/type_mapper.py
querky/backends/postgresql/asyncpg/__init__.py
querky/backends/postgresql/asyncpg/contract.py
querky/backends/postgresql/asyncpg/name_type_mapper.py
querky/mixins/__init__.py
querky/mixins/async_callbacks_mixin.py
querky/mixins/get_imports_mixin.py
querky/presets/__init__.py
querky/presets/asyncpg.py
querky/tools/__init__.py
querky/tools/query_folder.py
querky/type_constructors/__init__.py
querky/type_constructors/dataclass.py
querky/type_constructors/namedtuple.py
querky/type_constructors/typeddict.py
querky-0.1.2.dist-info/METADATA
querky-0.1.2.dist-info/WHEEL
querky-0.1.2.dist-info/licenses/LICENSE
querky-0.1.2.dist-info/RECORD
