Metadata-Version: 2.3
Name: querky
Version: 0.1.2
Summary: Turn your raw SQL queries into pure Python PEP484 type annotated functions with a single decorator.
Project-URL: Homepage, https://github.com/racinette/querky
Project-URL: Issues, https://github.com/racinette/querky/issues
Author-email: Andrei Karavatski <verolomnyy@gmail.com>
Maintainer-email: Andrei Karavatski <verolomnyy@gmail.com>
License: MIT License
License-File: LICENSE
Keywords: async,code generation,decorator,module generation,pgsql,postgres,postgresql,psql,sql
Classifier: Development Status :: 4 - Beta
Classifier: Intended Audience :: Developers
Classifier: License :: OSI Approved :: MIT License
Classifier: Operating System :: OS Independent
Classifier: Programming Language :: Python
Classifier: Programming Language :: Python :: 3
Classifier: Programming Language :: Python :: 3 :: Only
Classifier: Programming Language :: Python :: 3.10
Classifier: Programming Language :: Python :: 3.11
Classifier: Programming Language :: Python :: 3.12
Classifier: Programming Language :: Python :: 3.13
Classifier: Programming Language :: SQL
Classifier: Topic :: Database
Classifier: Topic :: Database :: Front-Ends
Classifier: Topic :: Software Development :: Code Generators
Classifier: Topic :: Software Development :: Libraries
Classifier: Topic :: Software Development :: Libraries :: Python Modules
Requires-Python: >=3.10
Provides-Extra: asyncpg
Requires-Dist: asyncpg; extra == 'asyncpg'
